jokeabc/__init__.py
jokeabc/joke_one.py
jokeabc/joke_two.py
cdreek_funny_jokes-0.1.dist-info/METADATA
cdreek_funny_jokes-0.1.dist-info/WHEEL
cdreek_funny_jokes-0.1.dist-info/top_level.txt
cdreek_funny_jokes-0.1.dist-info/RECORD
