Metadata-Version: 2.1
Name: cdreek-funny-jokes
Version: 0.1
Summary: The funniest joke in the world
Home-page: UNKNOWN
Author: UNKNOWN
Author-email: UNKNOWN
License: MIT
Platform: UNKNOWN
